odoo8_addon_account_cutoff_base-8.0.0.1.0.99.dev71-py3.8-nspkg.pth
odoo_addons/account_cutoff_base/__init__.py
odoo_addons/account_cutoff_base/__openerp__.py
odoo_addons/account_cutoff_base/account_cutoff.py
odoo_addons/account_cutoff_base/account_cutoff_view.xml
odoo_addons/account_cutoff_base/company.py
odoo_addons/account_cutoff_base/company_view.xml
odoo_addons/account_cutoff_base/i18n/account_cutoff_base.pot
odoo_addons/account_cutoff_base/i18n/am.po
odoo_addons/account_cutoff_base/i18n/ar.po
odoo_addons/account_cutoff_base/i18n/bg.po
odoo_addons/account_cutoff_base/i18n/bs.po
odoo_addons/account_cutoff_base/i18n/ca.po
odoo_addons/account_cutoff_base/i18n/ca_ES.po
odoo_addons/account_cutoff_base/i18n/cs.po
odoo_addons/account_cutoff_base/i18n/da.po
odoo_addons/account_cutoff_base/i18n/da_DK.po
odoo_addons/account_cutoff_base/i18n/de.po
odoo_addons/account_cutoff_base/i18n/el_GR.po
odoo_addons/account_cutoff_base/i18n/en_GB.po
odoo_addons/account_cutoff_base/i18n/es.po
odoo_addons/account_cutoff_base/i18n/es_AR.po
odoo_addons/account_cutoff_base/i18n/es_CL.po
odoo_addons/account_cutoff_base/i18n/es_CO.po
odoo_addons/account_cutoff_base/i18n/es_CR.po
odoo_addons/account_cutoff_base/i18n/es_DO.po
odoo_addons/account_cutoff_base/i18n/es_EC.po
odoo_addons/account_cutoff_base/i18n/es_ES.po
odoo_addons/account_cutoff_base/i18n/es_MX.po
odoo_addons/account_cutoff_base/i18n/es_PE.po
odoo_addons/account_cutoff_base/i18n/es_PY.po
odoo_addons/account_cutoff_base/i18n/es_VE.po
odoo_addons/account_cutoff_base/i18n/et.po
odoo_addons/account_cutoff_base/i18n/eu.po
odoo_addons/account_cutoff_base/i18n/fa.po
odoo_addons/account_cutoff_base/i18n/fi.po
odoo_addons/account_cutoff_base/i18n/fr.po
odoo_addons/account_cutoff_base/i18n/fr_CA.po
odoo_addons/account_cutoff_base/i18n/fr_CH.po
odoo_addons/account_cutoff_base/i18n/fr_FR.po
odoo_addons/account_cutoff_base/i18n/gl.po
odoo_addons/account_cutoff_base/i18n/gl_ES.po
odoo_addons/account_cutoff_base/i18n/he.po
odoo8_addon_account_cutoff_base-8.0.0.1.0.99.dev71.dist-info/METADATA
odoo8_addon_account_cutoff_base-8.0.0.1.0.99.dev71.dist-info/WHEEL
odoo8_addon_account_cutoff_base-8.0.0.1.0.99.dev71.dist-info/namespace_packages.txt
odoo8_addon_account_cutoff_base-8.0.0.1.0.99.dev71.dist-info/top_level.txt
odoo8_addon_account_cutoff_base-8.0.0.1.0.99.dev71.dist-info/RECORD
